{
  "produtos": [
    {
      "nome": "Cookietos Planner A5",
      "preco": "150,00",
      "imagem": "assets\\C-Cookietos-Planner.jpg",
      "id": 1
    },
    {
      "nome": "Ecobag Cookienho azul",
      "preco": "50,00",
      "imagem": "assets\\C-ecobag-azul.jpg",
      "id": 2
    },
    {
      "nome": "Porta copos Cookie",
      "preco": "35,00",
      "imagem": "assets\\C-coster-madeira.jpg",
      "id": 3
    },
    {
      "nome": "Caderno A5 Kitsune",
      "preco": "30,00",
      "imagem": "assets\\C-Caderno-raposa.jpg",
      "id": 4
    },
    {
      "nome": "Chaveiro Corvo",
      "preco": "20,00",
      "imagem": "assets\\C-chaveiro-halloween.jpg",
      "id": 5
    },
    {
      "nome": "Bloco de notas Universo",
      "preco": "12,00",
      "imagem": "assets\\C-block-menina.jpg",
      "id": 6
    },
    {
      "nome": "Postacard dragão",
      "preco": "10,00",
      "imagem": "assets\\C-Postcard-dragao.jpg",
      "id": 7
    },
    {
      "nome": "Postacard Matsuri",
      "preco": "10,00",
      "imagem": "assets\\C-postcard-Matsuri.jpg",
      "id": 8
    },
    {
      "nome": "Postcard Chiyochan",
      "preco": "10,00",
      "imagem": "assets\\C-Postacard-chiyochan.jpg",
      "id": 9
    },
    {
      "nome": "Cartela Cookienho ponkan",
      "preco": "12,00",
      "imagem": "assets\\C-cartela-cookie.jpg",
      "id": 10
    },
    {
      "nome": "Adesivo Corvo aquarela",
      "preco": "8,00",
      "imagem": "assets\\C-adesivo-Corvo.jpg",
      "id": 11
    },
    {
      "nome": "Adesivo Frieren",
      "preco": "10,00",
      "imagem": "assets\\C-adesivo-menina.jpg",
      "id": 12
    },
    {
      "nome": "Botton Capivarita",
      "preco": "8,00",
      "imagem": "assets\\C-botton-capivarita.jpg",
      "id": 13
    }
  ]
}